Metadata-Version: 2.4
Name: llama-index-postprocessor-colpali-rerank
Version: 0.3.1
Summary: llama-index postprocessor colpali-rerank integration
Author-email: Ravi Theja <ravi03071991@gmail.com>
License-Expression: MIT
License-File: LICENSE
Requires-Python: <4.0,>=3.9
Requires-Dist: colpali-engine<0.4.0,>=0.3.0
Requires-Dist: llama-index-core<0.15,>=0.13.0
Requires-Dist: setuptools
Requires-Dist: torch
Requires-Dist: transformers>=4.37.2
